tabstack/__init__.py
tabstack/_base_client.py
tabstack/_client.py
tabstack/_compat.py
tabstack/_constants.py
tabstack/_exceptions.py
tabstack/_files.py
tabstack/_models.py
tabstack/_qs.py
tabstack/_resource.py
tabstack/_response.py
tabstack/_streaming.py
tabstack/_types.py
tabstack/_version.py
tabstack/py.typed
tabstack/_utils/__init__.py
tabstack/_utils/_compat.py
tabstack/_utils/_datetime_parse.py
tabstack/_utils/_json.py
tabstack/_utils/_logs.py
tabstack/_utils/_proxy.py
tabstack/_utils/_reflection.py
tabstack/_utils/_resources_proxy.py
tabstack/_utils/_streams.py
tabstack/_utils/_sync.py
tabstack/_utils/_transform.py
tabstack/_utils/_typing.py
tabstack/_utils/_utils.py
tabstack/lib/.keep
tabstack/resources/__init__.py
tabstack/resources/agent.py
tabstack/resources/extract.py
tabstack/resources/generate.py
tabstack/types/__init__.py
tabstack/types/agent_automate_params.py
tabstack/types/agent_research_params.py
tabstack/types/automate_event.py
tabstack/types/extract_json_params.py
tabstack/types/extract_json_response.py
tabstack/types/extract_markdown_params.py
tabstack/types/extract_markdown_response.py
tabstack/types/generate_json_params.py
tabstack/types/generate_json_response.py
tabstack/types/research_event.py
tabstack-2.1.0.dist-info/METADATA
tabstack-2.1.0.dist-info/WHEEL
tabstack-2.1.0.dist-info/licenses/LICENSE
tabstack-2.1.0.dist-info/RECORD
